arsene/__init__.py
arsene/client.py
arsene/connection/base.py
arsene/connection/redis_client.py
arsene/data_convert.py
arsene/exceptions.py
arsene/key_builder.py
arsene/logger.py
arsene/schemas/redis.py
arsene-0.1.6.dist-info/LICENSE
arsene-0.1.6.dist-info/WHEEL
arsene-0.1.6.dist-info/METADATA
arsene-0.1.6.dist-info/RECORD
