Metadata-Version: 2.1
Name: arsene
Version: 0.1.6
Summary: Easy data cache management
Home-page: https://github.com/JeremyAndress/cobnut
License: MIT
Keywords: arsene,cache,decorator
Author: JeremyAndress
Author-email: jeremysilvasilva@gmail.com
Requires-Python: >=3.6,<4.0
Classifier: Development Status :: 3 - Alpha
Classifier: Intended Audience :: Developers
Classifier: Intended Audience :: Information Technology
Classifier: Intended Audience :: System Administrators
Classifier: License :: OSI Approved :: MIT License
Classifier: Programming Language :: Python :: 3
Classifier: Programming Language :: Python :: 3.6
Classifier: Programming Language :: Python :: 3.7
Classifier: Programming Language :: Python :: 3.8
Classifier: Programming Language :: Python :: 3.9
Provides-Extra: redis
Requires-Dist: pydantic (>=1.7.3,<2.0.0)
Requires-Dist: redis (>=3.5.3,<4.0.0); extra == "redis"
Project-URL: Repository, https://github.com/JeremyAndress/cobnut
